aratinga/.python-version
aratinga/__about__.py
aratinga/__init__.py
aratinga/apps.py
aratinga/forms.py
aratinga/importexport.py
aratinga/search_urls.py
aratinga/settings.py
aratinga/urls.py
aratinga/utils.py
aratinga/views.py
aratinga/wagtail_hooks.py
aratinga/widgets.py
aratinga/admin/__init__.py
aratinga/admin/apps.py
aratinga/admin/forms.py
aratinga/admin/loaders.py
aratinga/admin/middleware.py
aratinga/admin/models.py
aratinga/admin/settings.py
aratinga/admin/tests.py
aratinga/admin/thread.py
aratinga/admin/urls.py
aratinga/admin/views.py
aratinga/admin/wagtail_hooks.py
aratinga/admin/migrations/0001_initial.py
aratinga/admin/migrations/0002_alter_themesettings_theme.py
aratinga/admin/migrations/0003_remove_theme_is_active.py
aratinga/admin/migrations/0004_alter_theme_description.py
aratinga/admin/migrations/0005_delete_themesettings.py
aratinga/admin/migrations/0006_themesettings.py
aratinga/admin/migrations/__init__.py
aratinga/admin/templates/wagtailadmin/admin_base.html
aratinga/admin/templates/wagtailadmin/base.html
aratinga/admin/templates/wagtailadmin/login.html
aratinga/admin/templates/wagtailadmin/theme_settings.html
aratinga/admin/templates/wagtailadmin/block_forms/base_block_settings_struct.html
aratinga/bin/__init__.py
aratinga/blocks/__init__.py
aratinga/blocks/base_blocks.py
aratinga/blocks/component_blocks.py
aratinga/blocks/content_blocks.py
aratinga/blocks/html_blocks.py
aratinga/blocks/layout_blocks.py
aratinga/blocks/section_blocks.py
aratinga/locale/pt_BR/LC_MESSAGES/django.po
aratinga/migrations/0001_initial.py
aratinga/migrations/0002_genericsettings_sitesettings.py
aratinga/migrations/0003_alter_genericsettings_title_suffix.py
aratinga/migrations/0004_carousel_classifier_carouselslide_classifierterm.py
aratinga/migrations/0005_aratingapage_classifier_terms_aratingapage_tags.py
aratinga/migrations/0006_alter_genericsettings_title_suffix.py
aratinga/migrations/0007_template_templatepage.py
aratinga/migrations/0008_theme_themesettings.py
aratinga-0.1.0a0.dev3.dist-info/METADATA
aratinga-0.1.0a0.dev3.dist-info/WHEEL
aratinga-0.1.0a0.dev3.dist-info/entry_points.txt
aratinga-0.1.0a0.dev3.dist-info/licenses/LICENSE
aratinga-0.1.0a0.dev3.dist-info/RECORD
