Metadata-Version: 2.4
Name: aratinga
Version: 0.1.0a0.dev3
Summary: Wagtail + Voreios Extensions enabling rapid development of brasilian public educational-focused websites.
Project-URL: Source, https://github.com/roraimae/aratinga
Author-email: Roraimae <fabio@voreios.com.br>
License: BSD 3-Clause License
License-File: LICENSE
Requires-Python: >=3.12
Requires-Dist: django<5.3,>=5.2
Requires-Dist: wagtail<7.2,>=7.1
